odoo/addons/pos_ticket_salesman_firstname/README.rst
odoo/addons/pos_ticket_salesman_firstname/__init__.py
odoo/addons/pos_ticket_salesman_firstname/__manifest__.py
odoo/addons/pos_ticket_salesman_firstname/i18n/es.po
odoo/addons/pos_ticket_salesman_firstname/i18n/it.po
odoo/addons/pos_ticket_salesman_firstname/i18n/pos_ticket_salesman_firstname.pot
odoo/addons/pos_ticket_salesman_firstname/models/__init__.py
odoo/addons/pos_ticket_salesman_firstname/models/pos_config.py
odoo/addons/pos_ticket_salesman_firstname/readme/CONFIGURE.rst
odoo/addons/pos_ticket_salesman_firstname/readme/CONTRIBUTORS.rst
odoo/addons/pos_ticket_salesman_firstname/readme/DESCRIPTION.rst
odoo/addons/pos_ticket_salesman_firstname/readme/USAGE.rst
odoo/addons/pos_ticket_salesman_firstname/static/description/icon.png
odoo/addons/pos_ticket_salesman_firstname/static/description/index.html
odoo/addons/pos_ticket_salesman_firstname/static/description/receipt.png
odoo/addons/pos_ticket_salesman_firstname/static/src/js/models.js
odoo/addons/pos_ticket_salesman_firstname/static/src/xml/pos.xml
odoo/addons/pos_ticket_salesman_firstname/views/assets.xml
odoo/addons/pos_ticket_salesman_firstname/views/pos_config.xml
odoo12_addon_pos_ticket_salesman_firstname-12.0.1.0.0.99.dev8.dist-info/METADATA
odoo12_addon_pos_ticket_salesman_firstname-12.0.1.0.0.99.dev8.dist-info/WHEEL
odoo12_addon_pos_ticket_salesman_firstname-12.0.1.0.0.99.dev8.dist-info/top_level.txt
odoo12_addon_pos_ticket_salesman_firstname-12.0.1.0.0.99.dev8.dist-info/RECORD
